Metadata-Version: 2.0
Name: Thanatos
Version: 0.4.2
Summary: A Python library for generating EVE Online trivia questions.
Home-page: https://github.com/Regner/thanatos
Author: Regner Blok-Andersen
Author-email: regnerba@gmail.com
License: MIT License
Platform: UNKNOWN
Classifier: Development Status :: 4 - Beta
Classifier: License :: OSI Approved :: MIT License
Classifier: Intended Audience :: Developers
Classifier: Operating System :: OS Independent
Classifier: Programming Language :: Python :: 2.7
Classifier: Topic :: Games/Entertainment
Classifier: Topic :: Software Development :: Libraries :: Python Modules
Requires-Dist: mysqlclient (==1.3.6)
Requires-Dist: eveimageserver (==0.1.2)
Requires-Dist: mock (==1.0b1)
Requires-Dist: unittest2 (==0.5.1)
Requires-Dist: coverage (==3.7.1)
Requires-Dist: nose (==1.3.6)
Requires-Dist: coveralls (==1.0a2)
Requires-Dist: twine
